sphere_temp_conversion/__init__.py
sphere_temp_conversion/__version__.py
sphere_temp_conversion/converter.py
sphere_temp_conversion/errors.py
sphere_temp_conversion-0.1.1.dist-info/METADATA
sphere_temp_conversion-0.1.1.dist-info/WHEEL
sphere_temp_conversion-0.1.1.dist-info/top_level.txt
sphere_temp_conversion-0.1.1.dist-info/RECORD
