Metadata-Version: 2.1
Name: sphere-temp-conversion
Version: 0.1.1
Summary: Unofficial package to convert sample temperatures and setpoints for the Sphere Energy ASC-T - All-solid-state battery testing device. Not affiliated with Sphere Energy.
Home-page: https://github.com/thvranken/sphere_temp_conversion
Author: Thomas Vranken
Author-email: thvranken@gmail.com
License: GNU
Download-URL: https://pypi.org/project/sphere-temp-conversion/
Keywords: Sphere Energy,Temperature conversion,ASC-T
Platform: UNKNOWN
